dd_tmgbedu/__init__.py
dd_tmgbedu/dd.py
dd_tmgbedu-0.1.2.dist-info/METADATA
dd_tmgbedu-0.1.2.dist-info/WHEEL
dd_tmgbedu-0.1.2.dist-info/top_level.txt
dd_tmgbedu-0.1.2.dist-info/RECORD
