Metadata-Version: 2.2
Name: dd_tmgbedu
Version: 0.1.2
Summary: The missing `dd` function in python.
Author-email: Bedram Tamang <tmgbedu@gmail.com>
Project-URL: Homepage, https://github.com/bedus-creation/python_dd
Project-URL: Issues, https://github.com/bedus-creation/python_dd/issues
Classifier: Programming Language :: Python :: 3
Classifier: License :: OSI Approved :: MIT License
Classifier: Operating System :: OS Independent
Requires-Python: >=3.11
